apollo_py_numpy_robotics/__init__.py
apollo_py_numpy_robotics/robot_modules_runtime/__init__.py
apollo_py_numpy_robotics/robot_modules_runtime/urdf_numpy_module.py
apollo_py_numpy_robotics-0.0.1.dist-info/LICENSE
apollo_py_numpy_robotics-0.0.1.dist-info/METADATA
apollo_py_numpy_robotics-0.0.1.dist-info/WHEEL
apollo_py_numpy_robotics-0.0.1.dist-info/RECORD
