Metadata-Version: 2.1
Name: apollo-py-numpy-robotics
Version: 0.0.1
Summary: 
License: MIT
Author: Danny Rakita
Author-email: daniel.rakita@yale.edu
Requires-Python: >=3.10,<4.0
Classifier: License :: OSI Approved :: MIT License
Classifier: Programming Language :: Python :: 3
Classifier: Programming Language :: Python :: 3.10
Classifier: Programming Language :: Python :: 3.11
Classifier: Programming Language :: Python :: 3.12
Requires-Dist: apollo-py-numpy-core (>=0.0.1,<0.0.2)
